<?xml version="1.0" encoding="UTF-8"?>
<quest_scripts xmlns:xsi="http://www.w3.org/2001/XMLSchema-instance" xsi:noNamespaceSchemaLocation="quest_script_data.xsd">
<!--
    Quest Theobomos
	Make By (Encom)
 -->	
	<item_collecting id="3003" start_npc_ids="798137"/>
	<item_collecting id="3004" start_npc_ids="798136" action_item_ids="700338"/>
	<item_collecting id="3007" start_npc_ids="798141"/>
	<item_collecting id="3009" start_npc_ids="798150"/>
	<item_collecting id="3010" start_npc_ids="798143"/>
	<item_collecting id="3012" start_npc_ids="798149"/>
	<item_collecting id="3017" start_npc_ids="798144"/>
	<item_collecting id="3022" start_npc_ids="798138"/>
	<item_collecting id="3032" start_npc_ids="798168" action_item_ids="700374"/>
	<item_collecting id="3034" start_npc_ids="798155"/>
	<item_collecting id="3038" start_npc_ids="798200"/>
	<item_collecting id="3039" start_npc_ids="798200"/>
	<item_collecting id="3040" start_npc_ids="798202" action_item_ids="700375"/>
	<item_collecting id="3047" start_npc_ids="798208"/>
	<item_collecting id="3053" start_npc_ids="798189" end_npc_ids="798193"/>
	<item_collecting id="3054" start_npc_ids="798179" action_item_ids="700377"/>
	<item_collecting id="3059" start_npc_ids="798193"/>
	<item_collecting id="3061" start_npc_ids="798172"/>
	<item_collecting id="3062" start_npc_ids="798196"/>
	<item_collecting id="3063" start_npc_ids="205304"/>
	<item_collecting id="3077" start_npc_ids="798164"/>
	<item_collecting id="3078" start_npc_ids="798164"/>
	<item_collecting id="3084" start_npc_ids="798199"/>
	<item_collecting id="3089" start_npc_ids="798182"/>
	<item_collecting id="3099" start_npc_ids="798169" action_item_ids="700450" end_npc_ids="203792"/>
	<item_collecting id="3101" start_npc_ids="798199"/>
	<item_collecting id="3104" start_npc_ids="798206"/>
	<item_collecting id="3106" start_npc_ids="798168"/>
	<item_collecting id="3112" start_npc_ids="798168"/>
	
	<monster_hunt id="3002" start_npc_ids="798132">
		<monster var="0" end_var="3" npc_ids="213814 213815"/>
		<monster var="1" end_var="4" npc_ids="213816 213817"/>
	</monster_hunt>
	<monster_hunt id="3005" start_npc_ids="798138">
		<monster var="0" end_var="3" npc_ids="213812 213813"/>
		<monster var="1" end_var="6" npc_ids="213810 213811"/>
	</monster_hunt>
	<monster_hunt id="3011" start_npc_ids="798149">
		<monster var="0" end_var="6" npc_ids="213824 213825"/>
	</monster_hunt>
	<monster_hunt id="3014" start_npc_ids="798144">
		<monster var="0" end_var="5" npc_ids="213832 213833"/>
		<monster var="1" end_var="5" npc_ids="213836 213837"/>
	</monster_hunt>
	<monster_hunt id="3015" start_npc_ids="798135">
		<monster var="0" end_var="6" npc_ids="213830 213831"/>
		<monster var="1" end_var="6" npc_ids="213834 213835"/>
	</monster_hunt>
	<monster_hunt id="3016" start_npc_ids="798132">
		<monster var="0" end_var="1" npc_ids="213927"/>
	</monster_hunt>
	<monster_hunt id="3021" start_npc_ids="798133">
		<monster var="0" end_var="7" npc_ids="213838 213839"/>
		<monster var="1" end_var="5" npc_ids="213840 213841"/>
	</monster_hunt>
	<monster_hunt id="3033" start_npc_ids="798155">
		<monster var="0" end_var="7" npc_ids="214235 214236"/>
		<monster var="1" end_var="5" npc_ids="214238 214239"/>
	</monster_hunt>
	<monster_hunt id="3042" start_npc_ids="798159">
		<monster var="0" end_var="5" npc_ids="214229 214230"/>
	</monster_hunt>
	<monster_hunt id="3043" start_npc_ids="798159">
		<monster var="0" end_var="1" npc_ids="214572"/>
	</monster_hunt>
	<monster_hunt id="3045" start_npc_ids="798206">
		<monster var="0" end_var="7" npc_ids="214286"/>
		<monster var="1" end_var="3" npc_ids="214282"/>
	</monster_hunt>
	<monster_hunt id="3046" start_npc_ids="798208">
		<monster var="0" end_var="8" npc_ids="214298 214299"/>
		<monster var="1" end_var="5" npc_ids="214304 214305"/>
	</monster_hunt>
	<monster_hunt id="3051" start_npc_ids="798191">
		<monster var="0" end_var="8" npc_ids="214300"/>
		<monster var="1" end_var="5" npc_ids="214306"/>
	</monster_hunt>
	<monster_hunt id="3052" start_npc_ids="798189">
		<monster var="0" end_var="5" npc_ids="214702 214703"/>
		<monster var="1" end_var="4" npc_ids="214307 214308"/>
	</monster_hunt>
	<monster_hunt id="3075" start_npc_ids="798222" end_npc_ids="798158">
		<monster var="0" end_var="8" npc_ids="214173 214174"/>
		<monster var="1" end_var="7" npc_ids="214182 214183"/>
	</monster_hunt>
	<monster_hunt id="3079" start_npc_ids="798155">
		<monster var="0" end_var="6" npc_ids="214240 214241"/>
		<monster var="1" end_var="7" npc_ids="214295 214296"/>
	</monster_hunt>
	<monster_hunt id="3080" start_npc_ids="798201">
		<monster var="0" end_var="5" npc_ids="214265 214266"/>
		<monster var="1" end_var="7" npc_ids="214263 214264"/>
	</monster_hunt>
	<monster_hunt id="3094" start_npc_ids="798215">
		<monster var="0" end_var="10" npc_ids="214545 214546"/>
	</monster_hunt>
	<!-- Berserk Silikor -->
	<monster_hunt id="3097" start_npc_ids="798225">
		<monster var="0" end_var="1" npc_ids="237248"/>
	</monster_hunt>
	<!-- The Theobomos Syndrome -->
	<monster_hunt id="3098" start_npc_ids="798225">
		<monster var="0" end_var="1" npc_ids="237110"/>
	</monster_hunt>
	<monster_hunt id="3105" start_npc_ids="798158">
		<monster var="0" end_var="8" npc_ids="214202 214203"/>
		<monster var="1" end_var="8" npc_ids="214194 214195"/>
	</monster_hunt>
	<monster_hunt id="3110" start_npc_ids="798138">
		<monster var="0" end_var="4" npc_ids="213812 213813"/>
		<monster var="1" end_var="6" npc_ids="213810 213811"/>
	</monster_hunt>
	<monster_hunt id="3111" start_npc_ids="798154">
		<monster var="0" end_var="8" npc_ids="214173 214174"/>
		<monster var="1" end_var="7" npc_ids="214182 214183"/>
	</monster_hunt>
	<!-- [Coin/Group] Triroan In The Lab -->
	<monster_hunt id="3113" start_npc_ids="798225">
		<monster var="0" end_var="1" npc_ids="237250"/>
	</monster_hunt>
	<!-- Archaeologist Pyrrha -->
	<monster_hunt id="3121" start_npc_ids="798155" end_npc_ids="798225">
        <monster var="0" npc_ids="214615" end_var="1"/>
        <monster var="1" npc_ids="214616" end_var="1"/>
        <monster var="2" npc_ids="214617" end_var="1"/>
        <monster var="3" npc_ids="214618" end_var="1"/>
    </monster_hunt>
</quest_scripts>