<?xml version="1.0" encoding="UTF-8" standalone="yes"?>
<zones>
    <zone mapid="300300000" name="EMPYREAN_CRUCIBLE_300300000" area_type="POLYGON" zone_type="SUB" priority="17" flags="0">
        <points bottom="-59.678078" top="940.321922">
            <point x="-25.638538" y="-29.559425"/>
            <point x="2086.594727" y="-33.709763"/>
            <point x="2073.969971" y="2127.839600"/>
            <point x="-24.990360" y="2134.615723"/>
        </points>
    </zone>
    <zone mapid="300300000" name="WAITING_ROOM_01_300300000" area_type="POLYGON" zone_type="SUB" priority="14" flags="0">
        <points bottom="15.231571" top="165.231571">
            <point x="356.654663" y="325.817169"/>
            <point x="386.979980" y="325.865021"/>
            <point x="387.016846" y="372.623627"/>
            <point x="356.592651" y="372.652924"/>
        </points>
    </zone>
    <zone mapid="300300000" name="WAITING_ROOM_05_300300000" area_type="POLYGON" zone_type="SUB" priority="16" flags="0">
        <points bottom="330.935608" top="380.935608">
            <point x="1284.145752" y="802.641479"/>
            <point x="1284.097778" y="839.209534"/>
            <point x="1236.965332" y="839.246826"/>
            <point x="1236.935303" y="802.578979"/>
        </points>
    </zone>
    <zone mapid="300300000" name="WAITING_ROOM_06_300300000" area_type="POLYGON" zone_type="SUB" priority="16" flags="0">
        <points bottom="106.087433" top="156.087433">
            <point x="1600.023804" y="169.090851"/>
            <point x="1571.729736" y="158.178879"/>
            <point x="1588.450073" y="114.519539"/>
            <point x="1616.864014" y="125.394936"/>
        </points>
    </zone>
    <zone mapid="300300000" name="WAITING_ROOM_07_300300000" area_type="POLYGON" zone_type="SUB" priority="16" flags="0">
        <points bottom="456.286957" top="506.286957">
            <point x="1795.445068" y="772.363342"/>
            <point x="1825.770386" y="772.411194"/>
            <point x="1825.807251" y="819.169800"/>
            <point x="1795.383057" y="819.199097"/>
        </points>
    </zone>
    <zone mapid="300300000" name="WAITING_ROOM_08_300300000" area_type="POLYGON" zone_type="SUB" priority="16" flags="0">
        <points bottom="278.648224" top="328.648224">
            <point x="1754.256714" y="1747.482910"/>
            <point x="1755.362915" y="1717.177734"/>
            <point x="1802.094238" y="1718.772705"/>
            <point x="1801.061768" y="1749.179443"/>
        </points>
    </zone>
    <zone mapid="300300000" name="WAITING_ROOM_09_300300000" area_type="POLYGON" zone_type="SUB" priority="16" flags="0">
        <points bottom="287.652740" top="337.652740">
            <point x="1333.702515" y="1699.859009"/>
            <point x="1382.009644" y="1715.639282"/>
            <point x="1357.854370" y="1790.181274"/>
            <point x="1309.349731" y="1774.472778"/>
        </points>
    </zone>
    <zone mapid="300300000" name="WAITING_ROOM_10_300300000" area_type="POLYGON" zone_type="SUB" priority="14" flags="0">
        <points bottom="375.233643" top="425.233643">
            <point x="1740.026123" y="1287.773315"/>
            <point x="1723.478760" y="1258.705933"/>
            <point x="1767.146118" y="1234.644287"/>
            <point x="1783.162964" y="1269.530273"/>
        </points>
    </zone>
    <zone mapid="300300000" name="TRAINING_ROOM_01_300300000" area_type="POLYGON" zone_type="SUB" priority="13" flags="0">
        <points bottom="15.254490" top="165.254490">
            <point x="370.634033" y="343.422607"/>
            <point x="371.283264" y="347.010345"/>
            <point x="371.382141" y="350.690674"/>
            <point x="370.888092" y="354.436279"/>
            <point x="369.878082" y="358.078033"/>
            <point x="368.862274" y="360.372772"/>
            <point x="366.991455" y="363.517578"/>
            <point x="364.651123" y="366.333710"/>
            <point x="361.839600" y="368.811096"/>
            <point x="358.816589" y="370.762177"/>
            <point x="357.140533" y="371.756073"/>
            <point x="354.416595" y="373.205536"/>
            <point x="348.916321" y="375.459442"/>
            <point x="315.398102" y="376.100708"/>
            <point x="315.421539" y="323.435944"/>
            <point x="349.766846" y="323.787079"/>
            <point x="355.900421" y="326.232849"/>
            <point x="358.939850" y="327.636780"/>
            <point x="361.978241" y="329.746887"/>
            <point x="364.737091" y="332.280762"/>
            <point x="367.054260" y="335.218140"/>
            <point x="368.931366" y="338.337250"/>
        </points>
    </zone>
    <zone mapid="300300000" name="TRAINING_ROOM_05_300300000" area_type="POLYGON" zone_type="SUB" priority="15" flags="0">
        <points bottom="330.958527" top="380.958527">
            <point x="1266.500854" y="820.477539"/>
            <point x="1260.263306" y="821.223694"/>
            <point x="1254.091064" y="820.480469"/>
            <point x="1248.362549" y="818.080017"/>
            <point x="1243.400024" y="814.317993"/>
            <point x="1239.581055" y="809.349182"/>
            <point x="1237.085205" y="803.495239"/>
            <point x="1232.911499" y="792.662598"/>
            <point x="1242.058838" y="770.583984"/>
            <point x="1278.339111" y="770.592163"/>
            <point x="1288.635864" y="792.768066"/>
            <point x="1283.229004" y="803.370117"/>
            <point x="1280.839722" y="809.365417"/>
            <point x="1277.125488" y="814.280334"/>
            <point x="1272.179321" y="818.044434"/>
        </points>
    </zone>
    <zone mapid="300300000" name="TRAINING_ROOM_06_300300000" area_type="POLYGON" zone_type="SUB" priority="15" flags="0">
        <points bottom="105.921654" top="155.921654">
            <point x="1613.538086" y="177.582428"/>
            <point x="1602.703003" y="166.346954"/>
            <point x="1602.466187" y="155.058945"/>
            <point x="1605.126343" y="148.231369"/>
            <point x="1605.272217" y="142.417343"/>
            <point x="1611.827271" y="134.673050"/>
            <point x="1618.721924" y="120.560341"/>
            <point x="1645.622437" y="131.949341"/>
            <point x="1654.584961" y="160.390610"/>
            <point x="1644.408813" y="173.217865"/>
            <point x="1631.324097" y="180.100327"/>
        </points>
    </zone>
    <zone mapid="300300000" name="TRAINING_ROOM_07_300300000" area_type="POLYGON" zone_type="SUB" priority="15" flags="0">
        <points bottom="456.309875" top="506.309875">
            <point x="1809.634766" y="794.265747"/>
            <point x="1809.634277" y="798.000977"/>
            <point x="1809.221558" y="801.765137"/>
            <point x="1808.151489" y="805.274963"/>
            <point x="1807.098145" y="807.604004"/>
            <point x="1805.237305" y="810.734192"/>
            <point x="1802.876709" y="813.626038"/>
            <point x="1800.130005" y="816.152161"/>
            <point x="1794.945435" y="819.875183"/>
            <point x="1756.122681" y="830.847168"/>
            <point x="1756.169800" y="767.696960"/>
            <point x="1795.139404" y="773.144226"/>
            <point x="1796.314209" y="774.198608"/>
            <point x="1800.299561" y="776.963501"/>
            <point x="1802.993896" y="779.488464"/>
            <point x="1805.369385" y="782.417908"/>
            <point x="1807.223511" y="785.610107"/>
            <point x="1808.975098" y="790.729980"/>
        </points>
    </zone>
    <zone mapid="300300000" name="TRAINING_ROOM_08_300300000" area_type="POLYGON" zone_type="SUB" priority="15" flags="0">
        <points bottom="278.671143" top="328.671143">
            <point x="1776.548096" y="1735.519043"/>
            <point x="1781.967773" y="1735.881348"/>
            <point x="1786.931641" y="1737.122803"/>
            <point x="1791.420532" y="1739.557373"/>
            <point x="1795.096191" y="1742.118774"/>
            <point x="1797.850098" y="1745.582642"/>
            <point x="1799.887329" y="1749.444824"/>
            <point x="1804.662598" y="1763.536011"/>
            <point x="1794.137329" y="1790.009521"/>
            <point x="1757.879517" y="1787.859863"/>
            <point x="1749.763672" y="1761.573364"/>
            <point x="1755.022217" y="1747.815430"/>
            <point x="1757.762939" y="1744.731934"/>
            <point x="1761.121338" y="1741.559448"/>
            <point x="1765.010010" y="1739.120239"/>
            <point x="1768.747803" y="1737.382202"/>
            <point x="1772.520752" y="1736.202271"/>
        </points>
    </zone>
    <zone mapid="300300000" name="TRAINING_ROOM_09_300300000" area_type="POLYGON" zone_type="SUB" priority="15" flags="0">
        <points bottom="287.691132" top="337.691132">
            <point x="1345.973877" y="1744.673584"/>
            <point x="1343.834473" y="1749.872437"/>
            <point x="1342.064331" y="1753.618530"/>
            <point x="1339.731079" y="1757.063843"/>
            <point x="1337.565430" y="1759.484497"/>
            <point x="1332.655029" y="1764.424072"/>
            <point x="1328.134277" y="1767.362183"/>
            <point x="1323.575195" y="1770.051392"/>
            <point x="1316.986206" y="1772.549072"/>
            <point x="1309.490356" y="1773.354980"/>
            <point x="1301.712769" y="1773.839844"/>
            <point x="1285.762939" y="1770.650879"/>
            <point x="1254.108154" y="1747.629272"/>
            <point x="1272.908936" y="1689.810791"/>
            <point x="1313.487427" y="1688.492798"/>
            <point x="1332.813232" y="1700.938354"/>
            <point x="1337.625244" y="1706.266724"/>
            <point x="1341.495728" y="1711.846802"/>
            <point x="1345.110474" y="1718.109741"/>
            <point x="1346.054688" y="1722.044312"/>
            <point x="1347.082764" y="1726.101685"/>
            <point x="1347.544800" y="1730.810547"/>
            <point x="1347.701660" y="1735.257446"/>
            <point x="1347.008911" y="1740.258667"/>
        </points>
    </zone>
    <zone mapid="300300000" name="TRAINING_ROOM_10_300300000" area_type="POLYGON" zone_type="SUB" priority="13" flags="0">
        <points bottom="375.256531" top="425.256531">
            <point x="1753.296387" y="1265.857178"/>
            <point x="1756.825928" y="1264.586304"/>
            <point x="1760.905518" y="1263.550537"/>
            <point x="1765.508057" y="1263.040039"/>
            <point x="1769.732300" y="1263.213257"/>
            <point x="1774.022095" y="1264.533447"/>
            <point x="1777.924805" y="1266.107788"/>
            <point x="1781.828247" y="1268.795654"/>
            <point x="1784.133057" y="1271.049316"/>
            <point x="1792.493530" y="1281.020264"/>
            <point x="1792.700195" y="1304.917847"/>
            <point x="1759.300781" y="1319.086182"/>
            <point x="1741.157715" y="1302.696411"/>
            <point x="1740.270752" y="1288.138428"/>
            <point x="1740.616089" y="1284.188477"/>
            <point x="1741.642578" y="1280.095459"/>
            <point x="1743.450073" y="1275.951782"/>
            <point x="1746.184326" y="1272.153320"/>
            <point x="1749.139648" y="1269.170776"/>
        </points>
    </zone>
</zones>