<?xml version="1.0" encoding="UTF-8"?>
<quest_scripts xmlns:xsi="http://www.w3.org/2001/XMLSchema-instance" xsi:noNamespaceSchemaLocation="quest_script_data.xsd">
<!--
    Quest Field Warden's 4.8
	Make By (Encom)
 -->
	<report_to_many id="45010" end_npc_ids="799848">
		<npc_infos var="0" npc_id="204715" quest_dialog="1352"/>
		<npc_infos var="1" npc_id="799848" quest_dialog="2375" close_dialog="1009"/>
	</report_to_many>
	<report_to_many id="45011" end_npc_ids="799848">
		<npc_infos var="0" npc_id="204772" quest_dialog="1352"/>
		<npc_infos var="1" npc_id="799848" quest_dialog="2375" close_dialog="1009"/>
	</report_to_many>
	<report_to_many id="45017" end_npc_ids="799849">
		<npc_infos var="0" npc_id="205143" quest_dialog="1352"/>
		<npc_infos var="1" npc_id="799849" quest_dialog="2375" close_dialog="1009"/>
	</report_to_many>
	<report_to_many id="45018" end_npc_ids="799849">
		<npc_infos var="0" npc_id="205130" quest_dialog="1352"/>
		<npc_infos var="1" npc_id="799849" quest_dialog="2375" close_dialog="1009"/>
	</report_to_many>
	<report_to_many id="45024" end_npc_ids="799842 799843">
		<npc_infos var="0" npc_id="799244" quest_dialog="1352"/>
		<npc_infos var="1" npc_id="799842" quest_dialog="2375" close_dialog="1009"/>
		<npc_infos var="1" npc_id="799843" quest_dialog="2375" close_dialog="1009"/>
	</report_to_many>
	<report_to_many id="45025" end_npc_ids="799842 799843">
		<npc_infos var="0" npc_id="799271" quest_dialog="1352"/>
		<npc_infos var="1" npc_id="799842" quest_dialog="2375" close_dialog="1009"/>
		<npc_infos var="1" npc_id="799843" quest_dialog="2375" close_dialog="1009"/>
	</report_to_many>
	<report_to_many id="45026" end_npc_ids="799842 799843">
		<npc_infos var="0" npc_id="799285" quest_dialog="1352"/>
		<npc_infos var="1" npc_id="799842" quest_dialog="2375" close_dialog="1009"/>
		<npc_infos var="1" npc_id="799843" quest_dialog="2375" close_dialog="1009"/>
	</report_to_many>
	<report_to_many id="45027" end_npc_ids="799842 799843">
		<npc_infos var="0" npc_id="799305" quest_dialog="1352"/>
		<npc_infos var="1" npc_id="799842" quest_dialog="2375" close_dialog="1009"/>
		<npc_infos var="1" npc_id="799843" quest_dialog="2375" close_dialog="1009"/>
	</report_to_many>
	<report_to_many id="45028" end_npc_ids="799842 799843">
		<npc_infos var="0" npc_id="799314" quest_dialog="1352"/>
		<npc_infos var="1" npc_id="799842" quest_dialog="2375" close_dialog="1009"/>
		<npc_infos var="1" npc_id="799843" quest_dialog="2375" close_dialog="1009"/>
	</report_to_many>
	<report_to_many id="45029" end_npc_ids="799842 799843">
		<npc_infos var="0" npc_id="799354" quest_dialog="1352"/>
		<npc_infos var="1" npc_id="799842" quest_dialog="2375" close_dialog="1009"/>
		<npc_infos var="1" npc_id="799843" quest_dialog="2375" close_dialog="1009"/>
	</report_to_many>
	<report_to_many id="45030" end_npc_ids="799842 799843">
		<npc_infos var="0" npc_id="799360" quest_dialog="1352"/>
		<npc_infos var="1" npc_id="799842" quest_dialog="2375" close_dialog="1009"/>
		<npc_infos var="1" npc_id="799843" quest_dialog="2375" close_dialog="1009"/>
	</report_to_many>
	<!-- [일일] 오색 해안의 정보 -->
	<report_to_many id="45055" end_npc_ids="804931">
		<npc_infos var="0" npc_id="804902" quest_dialog="1352"/>
		<npc_infos var="1" npc_id="804931" quest_dialog="2375" close_dialog="1009"/>
	</report_to_many>
	<!-- [일일] 금빛 노을 숲 정보 -->
	<report_to_many id="45056" end_npc_ids="804932">
		<npc_infos var="0" npc_id="804729" quest_dialog="1352"/>
		<npc_infos var="1" npc_id="804932" quest_dialog="2375" close_dialog="1009"/>
	</report_to_many>
	<!-- [일일] 붉은 사막의 정보 -->
	<report_to_many id="45057" end_npc_ids="804933">
		<npc_infos var="0" npc_id="804924" quest_dialog="1352"/>
		<npc_infos var="1" npc_id="804933" quest_dialog="2375" close_dialog="1009"/>
	</report_to_many>
	
	<item_collecting id="45007" start_npc_ids="0" end_npc_ids="799848" action_item_ids="700800"/>
	<item_collecting id="45008" start_npc_ids="0" end_npc_ids="799848" action_item_ids="700801"/>
	<item_collecting id="45014" start_npc_ids="0" end_npc_ids="799849" action_item_ids="700803"/>
	<item_collecting id="45015" start_npc_ids="0" end_npc_ids="799849" action_item_ids="700804"/>
	<item_collecting id="45021" start_npc_ids="0" end_npc_ids="799842 799843" action_item_ids="700778"/>
	<item_collecting id="45022" start_npc_ids="0" end_npc_ids="799842 799843" action_item_ids="700779"/>
	<item_collecting id="45031" start_npc_ids="0" end_npc_ids="799848"/>
	<item_collecting id="45032" start_npc_ids="0" end_npc_ids="799848"/>
	<item_collecting id="45033" start_npc_ids="0" end_npc_ids="799848"/>
	<item_collecting id="45034" start_npc_ids="0" end_npc_ids="799848"/>
	<item_collecting id="45039" start_npc_ids="0" end_npc_ids="799849"/>
	<item_collecting id="45040" start_npc_ids="0" end_npc_ids="799849"/>
	<item_collecting id="45041" start_npc_ids="0" end_npc_ids="799849"/>
	<item_collecting id="45042" start_npc_ids="0" end_npc_ids="799849"/>
	<item_collecting id="45045" start_npc_ids="0" end_npc_ids="799842 799843"/>
	<item_collecting id="45046" start_npc_ids="0" end_npc_ids="799842 799843"/>
	<item_collecting id="45047" start_npc_ids="0" end_npc_ids="799842 799843"/>
	<item_collecting id="45048" start_npc_ids="0" end_npc_ids="799842 799843"/>
	<!-- [일일] 힘이 깃든 진주를 보급하라 -->
	<item_collecting id="45053" start_npc_ids="0" end_npc_ids="804930" action_item_ids="700754"/>
	<!-- [일일] 태고의 드라나를 보급하라 -->
	<item_collecting id="45054" start_npc_ids="0" end_npc_ids="804930" action_item_ids="700755"/>
	
	<monster_hunt id="45009" start_npc_ids="0" end_npc_ids="799848">
		<monster end_var="3" var="0" npc_ids="700802"/>
	</monster_hunt>
	<monster_hunt id="45016" start_npc_ids="0" end_npc_ids="799849">
		<monster end_var="3" var="0" npc_ids="700805"/>
	</monster_hunt>
	<monster_hunt id="45023" start_npc_ids="0" end_npc_ids="799842 799843">
		<monster end_var="3" var="0" npc_ids="700780"/>
	</monster_hunt>
	<monster_hunt id="45035" start_npc_ids="0" end_npc_ids="799848">
		<monster end_var="5" var="0" npc_ids="213009"/>
	</monster_hunt>
	<monster_hunt id="45036" start_npc_ids="0" end_npc_ids="799848">
		<monster end_var="5" var="0" npc_ids="213029"/>
	</monster_hunt>
	<monster_hunt id="45037" start_npc_ids="0" end_npc_ids="799848">
		<monster end_var="5" var="0" npc_ids="213080"/>
	</monster_hunt>
	<monster_hunt id="45038" start_npc_ids="0" end_npc_ids="799848">
		<monster end_var="5" var="0" npc_ids="213098"/>
	</monster_hunt>
	<monster_hunt id="45043" start_npc_ids="0" end_npc_ids="799849">
		<monster end_var="5" var="0" npc_ids="214373"/>
	</monster_hunt>
	<monster_hunt id="45044" start_npc_ids="0" end_npc_ids="799849">
		<monster end_var="5" var="0" npc_ids="214367"/>
	</monster_hunt>
	<monster_hunt id="45049" start_npc_ids="0" end_npc_ids="799842 799843">
		<monster end_var="5" var="0" npc_ids="216542"/>
	</monster_hunt>
	<monster_hunt id="45050" start_npc_ids="0" end_npc_ids="799842 799843">
		<monster end_var="5" var="0" npc_ids="215901"/>
	</monster_hunt>
	<monster_hunt id="45051" start_npc_ids="0" end_npc_ids="799842 799843">
		<monster end_var="5" var="0" npc_ids="216022"/>
	</monster_hunt>
	<!-- [일일] 엔샤르 결계석을 파괴하라 -->
	<monster_hunt id="45052" start_npc_ids="0" end_npc_ids="804930">
		<monster end_var="3" var="0" npc_ids="702753"/>
	</monster_hunt>
	<!-- [일일] 푸른 산호 디오나에를 처치하라 -->
	<monster_hunt id="45058" start_npc_ids="0" end_npc_ids="804931">
		<monster end_var="10" var="0" npc_ids="219678 219679"/>
	</monster_hunt>
	<!-- [일일] 화랑날개 퓨리를 처치하라 -->
	<monster_hunt id="45059" start_npc_ids="0" end_npc_ids="804931">
		<monster end_var="10" var="0" npc_ids="219688 219689"/>
	</monster_hunt>
	<!-- [일일] 등불 드라코비를 처치하라 -->
	<monster_hunt id="45060" start_npc_ids="0" end_npc_ids="804934">
		<monster end_var="10" var="0" npc_ids="219706 219707"/>
	</monster_hunt>
	<!-- [일일] 달빛 쉴룩을 처치하라 -->
	<monster_hunt id="45061" start_npc_ids="0" end_npc_ids="804932">
		<monster end_var="10" var="0" npc_ids="219720 219721"/>
	</monster_hunt>
	<!-- [일일] 물결 비늘 나가란트를 처치하라 -->
	<monster_hunt id="45062" start_npc_ids="0" end_npc_ids="804933">
		<monster end_var="10" var="0" npc_ids="219734 219735"/>
	</monster_hunt>
	<!-- [일일] 검은 코라스크를 처치하라 -->
	<monster_hunt id="45063" start_npc_ids="0" end_npc_ids="804935">
		<monster end_var="10" var="0" npc_ids="219754 219755"/>
	</monster_hunt>
	<!-- [일일] 코랄크롭스를 처치하라 -->
	<monster_hunt id="45064" start_npc_ids="0" end_npc_ids="804936">
		<monster end_var="10" var="0" npc_ids="219766 219767"/>
	</monster_hunt>
	<!-- [일일] 썩은 비늘 프릴파이맘을 처치하라 -->
	<monster_hunt id="45065" start_npc_ids="0" end_npc_ids="804937">
		<monster end_var="10" var="0" npc_ids="219797 219798"/>
	</monster_hunt>
</quest_scripts>